SCCAF/__init__.py
SCCAF-0.0.10.data/scripts/sccaf
SCCAF-0.0.10.data/scripts/sccaf-assess
SCCAF-0.0.10.data/scripts/sccaf-assess-merger
SCCAF-0.0.10.data/scripts/sccaf-regress-out
SCCAF-0.0.10.dist-info/LICENSE
SCCAF-0.0.10.dist-info/METADATA
SCCAF-0.0.10.dist-info/WHEEL
SCCAF-0.0.10.dist-info/top_level.txt
SCCAF-0.0.10.dist-info/RECORD
