Metadata-Version: 2.1
Name: SCCAF
Version: 0.0.10
Summary: Single-Cell Clustering Assessment Framework
Home-page: UNKNOWN
Author: Chichau Miau
Author-email: zmiao@ebi.ac.uk
License: MIT
Platform: UNKNOWN
Requires-Dist: numpy
Requires-Dist: pandas
Requires-Dist: louvain
Requires-Dist: scikit-learn
Requires-Dist: psutil
Requires-Dist: scanpy (==1.4.6)
